{
  "backedUpAt": "2026-01-27T11:23:24.833Z",
  "course": {
    "courseId": "PRODUCTIVITY_2026_HU",
    "name": "Termelékenység 2026: Hogyan kezelj csapatokat és időt",
    "language": "hu"
  },
  "lesson": {
    "dayNumber": 7,
    "title": "Napi/heti rendszer: reggeli ritual, napi huddle, heti áttekintés",
    "lessonId": "PRODUCTIVITY_2026_HU_DAY_07"
  },
  "questionCount": 3,
  "questions": [
    {
      "_id": "697766da9b3efa470445600d",
      "uuid": "90ab8419-a8f0-46b1-b392-64d7d0adf6d1",
      "questionType": "application",
      "difficulty": "MEDIUM",
      "question": "A leckében leírt \"gyakorlat (2 min): Fokuszsz...\" gyakorlatot hogyan implementálnád a saját munkádban?",
      "options": [
        "Lépésről lépésre követem a leckében leírt módszert, dokumentálom az eredményeket, és finomhangolom a folyamatot",
        "Egyszerre próbálom ki mindent",
        "Csak olvasom, nem alkalmazom",
        "Várok, amíg mások megcsinálják"
      ],
      "correctIndex": 0,
      "hashtags": [
        "#day7",
        "#hu",
        "#all-languages",
        "#productivity",
        "#intermediate",
        "#recall"
      ]
    },
    {
      "_id": "697766da9b3efa470445600e",
      "uuid": "19534994-c408-4917-b947-97f9d2c4d834",
      "questionType": "application",
      "difficulty": "MEDIUM",
      "question": "A leckében leírt \"gyakorlat (2 min): Fokuszsz...\" gyakorlatot hogyan implementálnád a saját munkádban?",
      "options": [
        "Lépésről lépésre követem a leckében leírt módszert, dokumentálom az eredményeket, és finomhangolom a folyamatot",
        "Egyszerre próbálom ki mindent",
        "Csak olvasom, nem alkalmazom",
        "Várok, amíg mások megcsinálják"
      ],
      "correctIndex": 0,
      "hashtags": [
        "#day7",
        "#hu",
        "#all-languages",
        "#productivity",
        "#intermediate",
        "#recall"
      ]
    },
    {
      "_id": "697766da9b3efa470445600f",
      "uuid": "cbf19334-f878-401a-b000-7ca14942f6e8",
      "questionType": "application",
      "difficulty": "MEDIUM",
      "question": "A leckében leírt \"gyakorlat (2 min): Fokuszsz...\" gyakorlatot hogyan implementálnád a saját munkádban?",
      "options": [
        "Lépésről lépésre követem a leckében leírt módszert, dokumentálom az eredményeket, és finomhangolom a folyamatot",
        "Egyszerre próbálom ki mindent",
        "Csak olvasom, nem alkalmazom",
        "Várok, amíg mások megcsinálják"
      ],
      "correctIndex": 0,
      "hashtags": [
        "#day7",
        "#hu",
        "#all-languages",
        "#productivity",
        "#intermediate",
        "#recall"
      ]
    }
  ]
}