{
  "backedUpAt": "2026-01-27T14:39:28.513Z",
  "courseId": "PRODUCTIVITY_2026_TR",
  "lessonId": "PRODUCTIVITY_2026_TR_DAY_11",
  "dayNumber": 11,
  "title": "Hedef Belirleme ve OKR'ler: Ne Başarmak İstiyorsunuz?",
  "content": "<h1>Hedef Belirleme ve OKR'ler: Ne Başarmak İstiyorsunuz?</h1>\n<p><em>Amaçsız verimlilik = sadece meşgul olmak.</em></p>\n<hr />\n<h2>Öğrenme Hedefleri</h2>\n<ul>\n<li>SMART hedefler belirleyin.</li>\n<li>OKR'leri (Hedefler ve Temel Sonuçlar) anlayın ve kullanın.</li>\n<li>Hedefleri haftalık/günlük görevlere bölün.</li>\n<li>İlerlemeyi izleyin ve kursu ayarlayın.</li>\n</ul>\n<hr />\n<h2>Neden Önemli</h2>\n<ul>\n<li><strong>Yön</strong>: Hedefler olmadan aktivite verimlilik değildir.</li>\n<li><strong>Motivasyon</strong>: SMART hedefler motivasyon yaratır.</li>\n<li><strong>Ölçüm</strong>: Başarılı olup olmadığınızı ancak ölçülebilirse bilebilirsiniz.</li>\n</ul>",
  "emailSubject": "Verimlilik 2026 – 11. Gün: Hedef Belirleme ve OKR'ler",
  "emailBody": "<h1>Verimlilik 2026 – 11. Gün</h1>\n<h2>Hedef Belirleme ve OKR'ler: Ne Başarmak İstiyorsunuz?</h2>\n<p>Bugün: SMART hedefler ve OKR'ler.</p>\n<p><a href=\"https://www.amanoba.com/tr/courses/PRODUCTIVITY_2026_TR/day/11\">Dersi aç →</a></p>"
}