{
  "backedUpAt": "2026-01-28T22:55:46.277Z",
  "course": {
    "courseId": "AI_30_DAY_EN",
    "name": "30-Day AI Catch-Up Program (EN)",
    "language": "en"
  },
  "lesson": {
    "dayNumber": 8,
    "title": "Fact-checking and source requests",
    "lessonId": "AI_30_DAY_EN_DAY_08"
  },
  "questionCount": 7,
  "questions": [
    {
      "_id": "697769fb27e27f61ac4143ca",
      "uuid": "eddb658a-3f23-4118-bb06-78d27399c041",
      "questionType": "application",
      "difficulty": "MEDIUM",
      "question": "How would you implement the practice \"exercise (10–15 min)\n\nPick a factual top...\" described in the lesson in your own work?",
      "options": [
        "I follow the method described in the lesson step by step, document the results, and refine the process",
        "I try everything at once",
        "I only read, I don't apply",
        "I wait for others to do it"
      ],
      "correctIndex": 0,
      "hashtags": [
        "#day8",
        "#en",
        "#all-languages",
        "#ai",
        "#intermediate",
        "#recall"
      ]
    },
    {
      "_id": "697769fb27e27f61ac4143cb",
      "uuid": "db10a0ed-3053-4fbd-ab08-37894f308d76",
      "questionType": "application",
      "difficulty": "MEDIUM",
      "question": "How would you implement the practice \"exercise (5–10 min)\nRewrite your QA chec...\" described in the lesson in your own work?",
      "options": [
        "I follow the method described in the lesson step by step, document the results, and refine the process",
        "I try everything at once",
        "I only read, I don't apply",
        "I wait for others to do it"
      ],
      "correctIndex": 0,
      "hashtags": [
        "#day8",
        "#en",
        "#all-languages",
        "#ai",
        "#intermediate",
        "#recall"
      ]
    },
    {
      "_id": "697769fb27e27f61ac4143cc",
      "uuid": "ec67de6e-79b7-4041-9db8-c44f40ac92ad",
      "questionType": "application",
      "difficulty": "MEDIUM",
      "question": "How would you implement the practice \"exercise (10–15 min)\n\nPick a factual top...\" described in the lesson in your own work?",
      "options": [
        "I follow the method described in the lesson step by step, document the results, and refine the process",
        "I try everything at once",
        "I only read, I don't apply",
        "I wait for others to do it"
      ],
      "correctIndex": 0,
      "hashtags": [
        "#day8",
        "#en",
        "#all-languages",
        "#ai",
        "#intermediate",
        "#recall"
      ]
    },
    {
      "_id": "697769fb27e27f61ac4143cd",
      "uuid": "7906b43f-1dfc-440d-ac07-45cef8a798db",
      "questionType": "critical-thinking",
      "difficulty": "HARD",
      "question": "How does the concept \"Fact-checking and source requests Reduce hallucina...\" mentioned in the lesson impact achieving your goals?",
      "options": [
        "As described in detail in the lesson, Fact-checking and source reque... increases effectiveness and reduces risk",
        "No significant impact",
        "Only matters theoretically",
        "Only an optional element"
      ],
      "correctIndex": 0,
      "hashtags": [
        "#day8",
        "#en",
        "#all-languages",
        "#ai",
        "#advanced",
        "#recall"
      ]
    },
    {
      "_id": "697769fb27e27f61ac4143ce",
      "uuid": "3d1cac27-fd88-480d-82bf-4092b4f1ed2e",
      "questionType": "recall",
      "difficulty": "MEDIUM",
      "question": "How important is Prompt in the context of Fact-checking and source requests as discussed in the lesson?",
      "options": [
        "As described in detail in the lesson, Prompt plays a crucial role in optimizing processes and achieving goals",
        "Only peripheral information with no significant role",
        "Only a theoretical concept with no practical application",
        "Not mentioned in the lesson"
      ],
      "correctIndex": 0,
      "hashtags": [
        "#day8",
        "#en",
        "#all-languages",
        "#ai",
        "#intermediate",
        "#recall"
      ]
    },
    {
      "_id": "697769fb27e27f61ac4143cf",
      "uuid": "345223f6-6516-41ce-abbf-97246cfae4c4",
      "questionType": "recall",
      "difficulty": "MEDIUM",
      "question": "How important is checking in the context of Fact-checking and source requests as discussed in the lesson?",
      "options": [
        "As described in detail in the lesson, checking plays a crucial role in optimizing processes and achieving goals",
        "Only peripheral information with no significant role",
        "Only a theoretical concept with no practical application",
        "Not mentioned in the lesson"
      ],
      "correctIndex": 0,
      "hashtags": [
        "#day8",
        "#en",
        "#all-languages",
        "#ai",
        "#intermediate",
        "#recall"
      ]
    },
    {
      "_id": "697769fb27e27f61ac4143d0",
      "uuid": "607aac97-cb73-42de-b5ad-7f4b72e21eb3",
      "questionType": "recall",
      "difficulty": "MEDIUM",
      "question": "How important is requests in the context of Fact-checking and source requests as discussed in the lesson?",
      "options": [
        "As described in detail in the lesson, requests plays a crucial role in optimizing processes and achieving goals",
        "Only peripheral information with no significant role",
        "Only a theoretical concept with no practical application",
        "Not mentioned in the lesson"
      ],
      "correctIndex": 0,
      "hashtags": [
        "#day8",
        "#en",
        "#all-languages",
        "#ai",
        "#intermediate",
        "#recall"
      ]
    }
  ]
}