{
  "backedUpAt": "2026-01-30T14:20:42.898Z",
  "course": {
    "courseId": "PRODUCTIVITY_2026_EN",
    "name": "Productivity 2026: How to Manage Teams and Time",
    "language": "en"
  },
  "lesson": {
    "dayNumber": 15,
    "title": "Teamwork and synergy (roles, responsibility, coordination)",
    "lessonId": "PRODUCTIVITY_2026_EN_DAY_15"
  },
  "questionCount": 5,
  "questions": [
    {
      "_id": "69787d9ba326286129da901b",
      "uuid": "5b135b1e-8b2b-4971-9614-e32b21f89724",
      "questionType": "application",
      "difficulty": "MEDIUM",
      "question": "You are applying \"Teamwork and synergy (roles, responsibility, coordination)\" this week. Which next step most directly turns intent into an outcome instead of extra activity?",
      "options": [
        "Pick one real scenario, apply the checklist, define a success metric/criterion, and review results at week’s end.",
        "Add more meetings and messages so progress is visible, then assume the outcome improved.",
        "Start multiple unrelated tasks to stay busy and increase the feeling of productivity.",
        "Delay action until the plan is perfect, because execution without certainty risks mistakes."
      ],
      "correctIndex": 0,
      "hashtags": [
        "#day15",
        "#en",
        "#course-productivity_2026_en",
        "#productivity",
        "#intermediate",
        "#application"
      ]
    },
    {
      "_id": "69787d9ba326286129da901c",
      "uuid": "36344272-db3e-4e46-826a-4c8ce226ef7a",
      "questionType": "application",
      "difficulty": "MEDIUM",
      "question": "Which option is the best example of a measurable metric/criterion for \"Teamwork and synergy (roles, responsibility, coordination)\" (so you can prove progress)?",
      "options": [
        "A specific number tracked weekly (e.g., decision latency, cycle time, time saved) with a threshold for success.",
        "A general intention like “be better at this”, without numbers or a deadline.",
        "A count of messages sent, regardless of whether outcomes improved.",
        "A feeling-based check (“did it feel productive?”) with no measurable signal."
      ],
      "correctIndex": 0,
      "hashtags": [
        "#day15",
        "#en",
        "#course-productivity_2026_en",
        "#productivity",
        "#intermediate",
        "#application"
      ]
    },
    {
      "_id": "69787d9ba326286129da901d",
      "uuid": "fa3096b4-d8a2-4014-bdfd-8b2b005e4480",
      "questionType": "application",
      "difficulty": "MEDIUM",
      "question": "In a \"Good vs Bad\" comparison for \"Teamwork and synergy (roles, responsibility, coordination)\", which option is closest to a “Good” implementation?",
      "options": [
        "Clear outcomes, explicit owners/criteria, and fewer distractions so execution produces measurable results.",
        "More activity (more meetings/updates) without decisions, owners, or measurable progress.",
        "More tools and dashboards without changing the process or defining success criteria.",
        "More urgency and overtime without adjusting constraints or simplifying the system."
      ],
      "correctIndex": 0,
      "hashtags": [
        "#day15",
        "#en",
        "#course-productivity_2026_en",
        "#productivity",
        "#intermediate",
        "#application"
      ]
    },
    {
      "_id": "69787d9ba326286129da901f",
      "uuid": "b1a45116-f118-4fcc-b8ce-ae758030b8e1",
      "questionType": "application",
      "difficulty": "MEDIUM",
      "question": "You want \"Teamwork and synergy (roles, responsibility, coordination)\" to work for a team, not just one person. Which change best makes it a scalable system?",
      "options": [
        "Document the checklist, define owners and success criteria, and run a lightweight cadence (review + adjustment).",
        "Rely on individual willpower and hope everyone copies the best performer’s habits.",
        "Make the process optional with no shared metrics so nobody feels pressured by measurement.",
        "Increase coordination time so everyone stays busy and visible, even if execution time drops."
      ],
      "correctIndex": 0,
      "hashtags": [
        "#day15",
        "#en",
        "#course-productivity_2026_en",
        "#productivity",
        "#intermediate",
        "#application"
      ]
    },
    {
      "_id": "69787d9ba326286129da9020",
      "uuid": "28f283d0-09b4-42e7-b562-ed5cc3788da9",
      "questionType": "critical-thinking",
      "difficulty": "HARD",
      "question": "What is the biggest risk if you implement \"Teamwork and synergy (roles, responsibility, coordination)\" incorrectly by adding more activity without changing outcomes?",
      "options": [
        "Constraints get consumed (time/energy/attention) while outcomes stagnate, so productivity drops even if work feels intense.",
        "Outcomes improve automatically because activity volume guarantees results in complex systems.",
        "Measurement becomes unnecessary because visible effort is a sufficient success signal.",
        "Decision quality improves because fatigue forces faster thinking and fewer debates."
      ],
      "correctIndex": 0,
      "hashtags": [
        "#day15",
        "#en",
        "#course-productivity_2026_en",
        "#productivity",
        "#advanced",
        "#critical-thinking"
      ]
    }
  ]
}